pynghttp2/__init__.py
pynghttp2/bindings.py
pynghttp2/http2.py
pynghttp2/messages.py
pynghttp2/nghttp2.py
pynghttp2/sessions.py
pynghttp2/streams.py
pynghttp2/typedefs.py
pynghttp2-0.3.2.dist-info/LICENSE.txt
pynghttp2-0.3.2.dist-info/METADATA
pynghttp2-0.3.2.dist-info/WHEEL
pynghttp2-0.3.2.dist-info/top_level.txt
pynghttp2-0.3.2.dist-info/RECORD
