Metadata-Version: 2.1
Name: pynghttp2
Version: 0.3.2
Summary: Asyncio bindings for libnghttp2 based on ctypes
Home-page: https://github.com/kahlertl/pynghttp2
Author: Lucas Kahlert
Author-email: lucas.kahlert@square-src.de
License: MIT
Project-URL: Source Code, https://github.com/kahlertl/pynghttp2/
Project-URL: Documentation, https://pynghttp2.readthedocs.io/
Project-URL: Bug Tracker, https://github.com/kahlertl/pynghttp2/issues
Keywords: HTTP/2 nghttp2 bindings asyncio ctypes
Platform: POSIX/Unix
Classifier: Development Status :: 3 - Alpha
Classifier: Environment :: Console
Classifier: Intended Audience :: Developers
Classifier: Natural Language :: English
Classifier: License :: OSI Approved :: MIT License
Classifier: Operating System :: POSIX
Classifier: Operating System :: Unix
Classifier: Programming Language :: Python
Classifier: Programming Language :: Python :: 3
Classifier: Programming Language :: Python :: 3.6
Classifier: Programming Language :: Python :: Implementation :: CPython
Classifier: Topic :: Software Development
License-File: LICENSE.txt
Provides-Extra: dev
Requires-Dist: pytest ; extra == 'dev'
Requires-Dist: pytest-asyncio ; extra == 'dev'
Requires-Dist: pytest-timeout ; extra == 'dev'
Requires-Dist: tox ; extra == 'dev'
